Workbook

Sheet Assumptions
A1: Peak 11 Media — Financial Model
A2: Edit the yellow cells. Every sheet recalculates live. Updated June 2026.
A4: INPUT ASSUMPTIONS
A5: Assumption | B5: Value | C5: Unit | D5: Notes
A6: Avg one-time build fee | B6: 1050 | C6: $ | D6: Starter $900 / Standard $1,200 blended
A7: Care plan price | B7: 49 | C7: $/mo | D7: Recurring hosting + edits + support
A8: Care-plan attach rate | B8: 0.4 | C8: % | D8: Share of new clients who take the plan
A9: Close rate (cold contacted) | B9: 0.03 | C9: % | D9: Of all contacted leads; demo-engaged far higher
A10: Demo-engaged close rate | B10: 0.2 | C10: % | D10: Of prospects who view a free demo build
A11: Monthly care-plan churn | B11: 0.03 | C11: % | D11: Plans cancelled per month
A12: Domain cost (pass-through) | B12: 12 | C12: $/yr | D12: Billed through to client; ~net zero
A13: Stripe processing | B13: 0.03 | C13: % | D13: Payment fee on all collected revenue
A14: Closer commission | B14: 0.15 | C14: % | D14: On one-time build revenue (10-20%)
A15: VA cost | B15: 600 | C15: $/mo | D15: Lead-gen / admin virtual assistant ($400-800)
A16: Hosting cost | B16: 0 | C16: $/mo | D16: GitHub Pages — free
A17: Tooling cost | B17: 0 | C17: $/mo | D17: Near zero
A19: SCENARIO LEVER
A20: The three scenario tabs differ by LEADS CONTACTED / MONTH (capacity ramp) and close rate.
A21: Conservative = solo, modest dials @2.5% close. Realistic = ramping help @3%. Optimistic = closer+VA, aggressive volume @3.5%.
A23: MRR ENGINE (steady-state targets)
A24: Active care plans for $5,000 MRR: | B24: =5000/Assumptions!$B$7
A25: Active care plans for $20,000 MRR: | B25: =20000/Assumptions!$B$7
A26: Once these plans are active, that income is recurring and largely passive.

Sheet Conservative
A1: Monthly Build-Up — Conservative
A2: Leads -> closes -> one-time + new care plans -> CUMULATIVE MRR (compounds) -> total revenue.
A4: Close rate (this scenario): | B4: 0.025
A6: Month | B6: Leads contacted | C6: Closes | D6: New care plans | E6: Churned plans | F6: Active care plans | G6: MRR (cumulative) | H6: One-time revenue | I6: Total revenue | J6: Stripe + comm cost | K6: Net revenue
A7: 1 | B7: 120 | C7: =B7*$B$4 | D7: =C7*Assumptions!$B$8 | E7: 0 | F7: =D7-E7 | G7: =F7*Assumptions!$B$7 | H7: =C7*Assumptions!$B$6 | I7: =G7+H7 | J7: =I7*Assumptions!$B$13+H7*Assumptions!$B$14+Assumptions!$B$15 | K7: =I7-J7
A8: 2 | B8: 140 | C8: =B8*$B$4 | D8: =C8*Assumptions!$B$8 | E8: =F7*Assumptions!$B$11 | F8: =F7-E8+D8 | G8: =F8*Assumptions!$B$7 | H8: =C8*Assumptions!$B$6 | I8: =G8+H8 | J8: =I8*Assumptions!$B$13+H8*Assumptions!$B$14+Assumptions!$B$15 | K8: =I8-J8
A9: 3 | B9: 150 | C9: =B9*$B$4 | D9: =C9*Assumptions!$B$8 | E9: =F8*Assumptions!$B$11 | F9: =F8-E9+D9 | G9: =F9*Assumptions!$B$7 | H9: =C9*Assumptions!$B$6 | I9: =G9+H9 | J9: =I9*Assumptions!$B$13+H9*Assumptions!$B$14+Assumptions!$B$15 | K9: =I9-J9
A10: 4 | B10: 160 | C10: =B10*$B$4 | D10: =C10*Assumptions!$B$8 | E10: =F9*Assumptions!$B$11 | F10: =F9-E10+D10 | G10: =F10*Assumptions!$B$7 | H10: =C10*Assumptions!$B$6 | I10: =G10+H10 | J10: =I10*Assumptions!$B$13+H10*Assumptions!$B$14+Assumptions!$B$15 | K10: =I10-J10
A11: 5 | B11: 170 | C11: =B11*$B$4 | D11: =C11*Assumptions!$B$8 | E11: =F10*Assumptions!$B$11 | F11: =F10-E11+D11 | G11: =F11*Assumptions!$B$7 | H11: =C11*Assumptions!$B$6 | I11: =G11+H11 | J11: =I11*Assumptions!$B$13+H11*Assumptions!$B$14+Assumptions!$B$15 | K11: =I11-J11
A12: 6 | B12: 180 | C12: =B12*$B$4 | D12: =C12*Assumptions!$B$8 | E12: =F11*Assumptions!$B$11 | F12: =F11-E12+D12 | G12: =F12*Assumptions!$B$7 | H12: =C12*Assumptions!$B$6 | I12: =G12+H12 | J12: =I12*Assumptions!$B$13+H12*Assumptions!$B$14+Assumptions!$B$15 | K12: =I12-J12
A13: 7 | B13: 190 | C13: =B13*$B$4 | D13: =C13*Assumptions!$B$8 | E13: =F12*Assumptions!$B$11 | F13: =F12-E13+D13 | G13: =F13*Assumptions!$B$7 | H13: =C13*Assumptions!$B$6 | I13: =G13+H13 | J13: =I13*Assumptions!$B$13+H13*Assumptions!$B$14+Assumptions!$B$15 | K13: =I13-J13
A14: 8 | B14: 200 | C14: =B14*$B$4 | D14: =C14*Assumptions!$B$8 | E14: =F13*Assumptions!$B$11 | F14: =F13-E14+D14 | G14: =F14*Assumptions!$B$7 | H14: =C14*Assumptions!$B$6 | I14: =G14+H14 | J14: =I14*Assumptions!$B$13+H14*Assumptions!$B$14+Assumptions!$B$15 | K14: =I14-J14
A15: 9 | B15: 210 | C15: =B15*$B$4 | D15: =C15*Assumptions!$B$8 | E15: =F14*Assumptions!$B$11 | F15: =F14-E15+D15 | G15: =F15*Assumptions!$B$7 | H15: =C15*Assumptions!$B$6 | I15: =G15+H15 | J15: =I15*Assumptions!$B$13+H15*Assumptions!$B$14+Assumptions!$B$15 | K15: =I15-J15
A16: 10 | B16: 220 | C16: =B16*$B$4 | D16: =C16*Assumptions!$B$8 | E16: =F15*Assumptions!$B$11 | F16: =F15-E16+D16 | G16: =F16*Assumptions!$B$7 | H16: =C16*Assumptions!$B$6 | I16: =G16+H16 | J16: =I16*Assumptions!$B$13+H16*Assumptions!$B$14+Assumptions!$B$15 | K16: =I16-J16
A17: 11 | B17: 230 | C17: =B17*$B$4 | D17: =C17*Assumptions!$B$8 | E17: =F16*Assumptions!$B$11 | F17: =F16-E17+D17 | G17: =F17*Assumptions!$B$7 | H17: =C17*Assumptions!$B$6 | I17: =G17+H17 | J17: =I17*Assumptions!$B$13+H17*Assumptions!$B$14+Assumptions!$B$15 | K17: =I17-J17
A18: 12 | B18: 240 | C18: =B18*$B$4 | D18: =C18*Assumptions!$B$8 | E18: =F17*Assumptions!$B$11 | F18: =F17-E18+D18 | G18: =F18*Assumptions!$B$7 | H18: =C18*Assumptions!$B$6 | I18: =G18+H18 | J18: =I18*Assumptions!$B$13+H18*Assumptions!$B$14+Assumptions!$B$15 | K18: =I18-J18
A19: YEAR 1 | G19: =G18 | H19: =SUM(H7:H18) | I19: =SUM(I7:I18) | J19: =SUM(J7:J18) | K19: =SUM(K7:K18)

Sheet Realistic
A1: Monthly Build-Up — Realistic
A2: Leads -> closes -> one-time + new care plans -> CUMULATIVE MRR (compounds) -> total revenue.
A4: Close rate (this scenario): | B4: 0.03
A6: Month | B6: Leads contacted | C6: Closes | D6: New care plans | E6: Churned plans | F6: Active care plans | G6: MRR (cumulative) | H6: One-time revenue | I6: Total revenue | J6: Stripe + comm cost | K6: Net revenue
A7: 1 | B7: 180 | C7: =B7*$B$4 | D7: =C7*Assumptions!$B$8 | E7: 0 | F7: =D7-E7 | G7: =F7*Assumptions!$B$7 | H7: =C7*Assumptions!$B$6 | I7: =G7+H7 | J7: =I7*Assumptions!$B$13+H7*Assumptions!$B$14+Assumptions!$B$15 | K7: =I7-J7
A8: 2 | B8: 220 | C8: =B8*$B$4 | D8: =C8*Assumptions!$B$8 | E8: =F7*Assumptions!$B$11 | F8: =F7-E8+D8 | G8: =F8*Assumptions!$B$7 | H8: =C8*Assumptions!$B$6 | I8: =G8+H8 | J8: =I8*Assumptions!$B$13+H8*Assumptions!$B$14+Assumptions!$B$15 | K8: =I8-J8
A9: 3 | B9: 260 | C9: =B9*$B$4 | D9: =C9*Assumptions!$B$8 | E9: =F8*Assumptions!$B$11 | F9: =F8-E9+D9 | G9: =F9*Assumptions!$B$7 | H9: =C9*Assumptions!$B$6 | I9: =G9+H9 | J9: =I9*Assumptions!$B$13+H9*Assumptions!$B$14+Assumptions!$B$15 | K9: =I9-J9
A10: 4 | B10: 300 | C10: =B10*$B$4 | D10: =C10*Assumptions!$B$8 | E10: =F9*Assumptions!$B$11 | F10: =F9-E10+D10 | G10: =F10*Assumptions!$B$7 | H10: =C10*Assumptions!$B$6 | I10: =G10+H10 | J10: =I10*Assumptions!$B$13+H10*Assumptions!$B$14+Assumptions!$B$15 | K10: =I10-J10
A11: 5 | B11: 340 | C11: =B11*$B$4 | D11: =C11*Assumptions!$B$8 | E11: =F10*Assumptions!$B$11 | F11: =F10-E11+D11 | G11: =F11*Assumptions!$B$7 | H11: =C11*Assumptions!$B$6 | I11: =G11+H11 | J11: =I11*Assumptions!$B$13+H11*Assumptions!$B$14+Assumptions!$B$15 | K11: =I11-J11
A12: 6 | B12: 380 | C12: =B12*$B$4 | D12: =C12*Assumptions!$B$8 | E12: =F11*Assumptions!$B$11 | F12: =F11-E12+D12 | G12: =F12*Assumptions!$B$7 | H12: =C12*Assumptions!$B$6 | I12: =G12+H12 | J12: =I12*Assumptions!$B$13+H12*Assumptions!$B$14+Assumptions!$B$15 | K12: =I12-J12
A13: 7 | B13: 420 | C13: =B13*$B$4 | D13: =C13*Assumptions!$B$8 | E13: =F12*Assumptions!$B$11 | F13: =F12-E13+D13 | G13: =F13*Assumptions!$B$7 | H13: =C13*Assumptions!$B$6 | I13: =G13+H13 | J13: =I13*Assumptions!$B$13+H13*Assumptions!$B$14+Assumptions!$B$15 | K13: =I13-J13
A14: 8 | B14: 460 | C14: =B14*$B$4 | D14: =C14*Assumptions!$B$8 | E14: =F13*Assumptions!$B$11 | F14: =F13-E14+D14 | G14: =F14*Assumptions!$B$7 | H14: =C14*Assumptions!$B$6 | I14: =G14+H14 | J14: =I14*Assumptions!$B$13+H14*Assumptions!$B$14+Assumptions!$B$15 | K14: =I14-J14
A15: 9 | B15: 500 | C15: =B15*$B$4 | D15: =C15*Assumptions!$B$8 | E15: =F14*Assumptions!$B$11 | F15: =F14-E15+D15 | G15: =F15*Assumptions!$B$7 | H15: =C15*Assumptions!$B$6 | I15: =G15+H15 | J15: =I15*Assumptions!$B$13+H15*Assumptions!$B$14+Assumptions!$B$15 | K15: =I15-J15
A16: 10 | B16: 540 | C16: =B16*$B$4 | D16: =C16*Assumptions!$B$8 | E16: =F15*Assumptions!$B$11 | F16: =F15-E16+D16 | G16: =F16*Assumptions!$B$7 | H16: =C16*Assumptions!$B$6 | I16: =G16+H16 | J16: =I16*Assumptions!$B$13+H16*Assumptions!$B$14+Assumptions!$B$15 | K16: =I16-J16
A17: 11 | B17: 580 | C17: =B17*$B$4 | D17: =C17*Assumptions!$B$8 | E17: =F16*Assumptions!$B$11 | F17: =F16-E17+D17 | G17: =F17*Assumptions!$B$7 | H17: =C17*Assumptions!$B$6 | I17: =G17+H17 | J17: =I17*Assumptions!$B$13+H17*Assumptions!$B$14+Assumptions!$B$15 | K17: =I17-J17
A18: 12 | B18: 620 | C18: =B18*$B$4 | D18: =C18*Assumptions!$B$8 | E18: =F17*Assumptions!$B$11 | F18: =F17-E18+D18 | G18: =F18*Assumptions!$B$7 | H18: =C18*Assumptions!$B$6 | I18: =G18+H18 | J18: =I18*Assumptions!$B$13+H18*Assumptions!$B$14+Assumptions!$B$15 | K18: =I18-J18
A19: YEAR 1 | G19: =G18 | H19: =SUM(H7:H18) | I19: =SUM(I7:I18) | J19: =SUM(J7:J18) | K19: =SUM(K7:K18)

Sheet Optimistic
A1: Monthly Build-Up — Optimistic
A2: Leads -> closes -> one-time + new care plans -> CUMULATIVE MRR (compounds) -> total revenue.
A4: Close rate (this scenario): | B4: 0.035
A6: Month | B6: Leads contacted | C6: Closes | D6: New care plans | E6: Churned plans | F6: Active care plans | G6: MRR (cumulative) | H6: One-time revenue | I6: Total revenue | J6: Stripe + comm cost | K6: Net revenue
A7: 1 | B7: 250 | C7: =B7*$B$4 | D7: =C7*Assumptions!$B$8 | E7: 0 | F7: =D7-E7 | G7: =F7*Assumptions!$B$7 | H7: =C7*Assumptions!$B$6 | I7: =G7+H7 | J7: =I7*Assumptions!$B$13+H7*Assumptions!$B$14+Assumptions!$B$15 | K7: =I7-J7
A8: 2 | B8: 320 | C8: =B8*$B$4 | D8: =C8*Assumptions!$B$8 | E8: =F7*Assumptions!$B$11 | F8: =F7-E8+D8 | G8: =F8*Assumptions!$B$7 | H8: =C8*Assumptions!$B$6 | I8: =G8+H8 | J8: =I8*Assumptions!$B$13+H8*Assumptions!$B$14+Assumptions!$B$15 | K8: =I8-J8
A9: 3 | B9: 400 | C9: =B9*$B$4 | D9: =C9*Assumptions!$B$8 | E9: =F8*Assumptions!$B$11 | F9: =F8-E9+D9 | G9: =F9*Assumptions!$B$7 | H9: =C9*Assumptions!$B$6 | I9: =G9+H9 | J9: =I9*Assumptions!$B$13+H9*Assumptions!$B$14+Assumptions!$B$15 | K9: =I9-J9
A10: 4 | B10: 480 | C10: =B10*$B$4 | D10: =C10*Assumptions!$B$8 | E10: =F9*Assumptions!$B$11 | F10: =F9-E10+D10 | G10: =F10*Assumptions!$B$7 | H10: =C10*Assumptions!$B$6 | I10: =G10+H10 | J10: =I10*Assumptions!$B$13+H10*Assumptions!$B$14+Assumptions!$B$15 | K10: =I10-J10
A11: 5 | B11: 560 | C11: =B11*$B$4 | D11: =C11*Assumptions!$B$8 | E11: =F10*Assumptions!$B$11 | F11: =F10-E11+D11 | G11: =F11*Assumptions!$B$7 | H11: =C11*Assumptions!$B$6 | I11: =G11+H11 | J11: =I11*Assumptions!$B$13+H11*Assumptions!$B$14+Assumptions!$B$15 | K11: =I11-J11
A12: 6 | B12: 640 | C12: =B12*$B$4 | D12: =C12*Assumptions!$B$8 | E12: =F11*Assumptions!$B$11 | F12: =F11-E12+D12 | G12: =F12*Assumptions!$B$7 | H12: =C12*Assumptions!$B$6 | I12: =G12+H12 | J12: =I12*Assumptions!$B$13+H12*Assumptions!$B$14+Assumptions!$B$15 | K12: =I12-J12
A13: 7 | B13: 720 | C13: =B13*$B$4 | D13: =C13*Assumptions!$B$8 | E13: =F12*Assumptions!$B$11 | F13: =F12-E13+D13 | G13: =F13*Assumptions!$B$7 | H13: =C13*Assumptions!$B$6 | I13: =G13+H13 | J13: =I13*Assumptions!$B$13+H13*Assumptions!$B$14+Assumptions!$B$15 | K13: =I13-J13
A14: 8 | B14: 820 | C14: =B14*$B$4 | D14: =C14*Assumptions!$B$8 | E14: =F13*Assumptions!$B$11 | F14: =F13-E14+D14 | G14: =F14*Assumptions!$B$7 | H14: =C14*Assumptions!$B$6 | I14: =G14+H14 | J14: =I14*Assumptions!$B$13+H14*Assumptions!$B$14+Assumptions!$B$15 | K14: =I14-J14
A15: 9 | B15: 920 | C15: =B15*$B$4 | D15: =C15*Assumptions!$B$8 | E15: =F14*Assumptions!$B$11 | F15: =F14-E15+D15 | G15: =F15*Assumptions!$B$7 | H15: =C15*Assumptions!$B$6 | I15: =G15+H15 | J15: =I15*Assumptions!$B$13+H15*Assumptions!$B$14+Assumptions!$B$15 | K15: =I15-J15
A16: 10 | B16: 1020 | C16: =B16*$B$4 | D16: =C16*Assumptions!$B$8 | E16: =F15*Assumptions!$B$11 | F16: =F15-E16+D16 | G16: =F16*Assumptions!$B$7 | H16: =C16*Assumptions!$B$6 | I16: =G16+H16 | J16: =I16*Assumptions!$B$13+H16*Assumptions!$B$14+Assumptions!$B$15 | K16: =I16-J16
A17: 11 | B17: 1120 | C17: =B17*$B$4 | D17: =C17*Assumptions!$B$8 | E17: =F16*Assumptions!$B$11 | F17: =F16-E17+D17 | G17: =F17*Assumptions!$B$7 | H17: =C17*Assumptions!$B$6 | I17: =G17+H17 | J17: =I17*Assumptions!$B$13+H17*Assumptions!$B$14+Assumptions!$B$15 | K17: =I17-J17
A18: 12 | B18: 1220 | C18: =B18*$B$4 | D18: =C18*Assumptions!$B$8 | E18: =F17*Assumptions!$B$11 | F18: =F17-E18+D18 | G18: =F18*Assumptions!$B$7 | H18: =C18*Assumptions!$B$6 | I18: =G18+H18 | J18: =I18*Assumptions!$B$13+H18*Assumptions!$B$14+Assumptions!$B$15 | K18: =I18-J18
A19: YEAR 1 | G19: =G18 | H19: =SUM(H7:H18) | I19: =SUM(I7:I18) | J19: =SUM(J7:J18) | K19: =SUM(K7:K18)

Sheet MRR Engine
A1: The MRR Engine — How $49/mo Stacks Into Passive Income
A2: Every closed client who takes the care plan adds $49/mo that recurs with little ongoing work.
A4: Active care plans | B4: Monthly recurring revenue | C4: Milestone
A5: 10 | B5: =A5*Assumptions!$B$7
A6: 25 | B6: =A6*Assumptions!$B$7
A7: 50 | B7: =A7*Assumptions!$B$7
A8: 75 | B8: =A8*Assumptions!$B$7
A9: 100 | B9: =A9*Assumptions!$B$7 | C9: ≈ $5k/mo target
A10: 150 | B10: =A10*Assumptions!$B$7
A11: 200 | B11: =A11*Assumptions!$B$7
A12: 300 | B12: =A12*Assumptions!$B$7
A13: 408 | B13: =A13*Assumptions!$B$7 | C13: ≈ $20k/mo target
A15: At ~40% attach, every ~2.5 closed builds adds one care plan. The care book is the asset; one-time fees fund growth.

Sheet Break-Evens
A1: Hire Break-Evens — When Each Role Pays for Itself
A2: A hire is justified the moment the revenue they unlock exceeds their cost.
A4: VIRTUAL ASSISTANT ($400-800/mo)
A5: VA monthly cost: | B5: =Assumptions!$B$15
A6: Gross profit per build (after Stripe+comm): | B6: =Assumptions!$B$6*(1-Assumptions!$B$13-Assumptions!$B$14)
A7: Builds/mo the VA must enable to break even: | B7: =B5/B6
A8: ...or in recurring care plans alone: | B8: =B5/Assumptions!$B$7
A9: A VA pays for itself by enabling ~1 extra build OR ~12 active care plans per month.
A11: CLOSER (10-20% commission, performance-based)
A12: Commission rate: | B12: =Assumptions!$B$14
A13: Cost per closed build (commission): | B13: =Assumptions!$B$6*Assumptions!$B$14
A14: Net to Peak 11 per build the closer brings: | B14: =Assumptions!$B$6*(1-Assumptions!$B$14-Assumptions!$B$13)
A15: Break-even: closer is self-funding from the FIRST close (paid only on results).
A16: Plus every build the closer lands seeds a recurring care plan at ~40% attach — pure upside.

Sheet Summary
A1: Headline — Timeline to $5k/mo and $20k/mo
A2: Realistic path, with conservative and optimistic brackets.
A4: Scenario | B4: Close rate | C4: Month to $5k/mo total | D4: Month to $20k/mo total | E4: Month to $5k MRR | F4: Active plans @ month 12 | G4: MRR @ month 12 | H4: Year-1 total rev
A5: Conservative | B5: 0.025 | C5: 7 | D5: 12+ | E5: 12+ | F5: 19 | G5: 940 | H5: 63725
A6: Realistic | B6: 0.03 | C6: 1 | D6: 12 | E6: 12+ | F6: 51 | G6: 2487 | H6: 164860
A7: Optimistic | B7: 0.035 | C7: 1 | D7: 6 | E7: 12 | F7: 105 | G7: 5166 | H7: 337918
A9: THE ANSWER (Realistic)
A10: • $5k/mo sustained total revenue: ~month 1. $20k/mo sustained: ~month 12.
A11: • To hold $5k/mo you need ~5 closes/mo (~180 leads contacted) plus a compounding care book.
A12: • $5k of PURE recurring MRR = ~102 active care plans; $20k MRR = ~408 plans.
A13: • Headcount: solo to $5k/mo; add a VA (lead-gen) and a commission closer to push toward $20k/mo.
A14: • The compounding care plans are what turn this from a hustle into a passive, sellable asset.
